jupytools/__init__.py
jupytools/__main__.py
jupytools/debug.py
jupytools/export.py
jupytools/syspath.py
jupytools/version.py
jupytools-0.1.5.dist-info/LICENSE
jupytools-0.1.5.dist-info/METADATA
jupytools-0.1.5.dist-info/WHEEL
jupytools-0.1.5.dist-info/top_level.txt
jupytools-0.1.5.dist-info/RECORD
