Metadata-Version: 2.1
Name: jupytools
Version: 0.1.5
Summary: A set of utilities making Jupyter development a bit easier
Home-page: https://github.com/devforfu/jupytools
Maintainer: devforfu
License: UNKNOWN
Download-URL: https://github.com/devforfu/jupytools/archive/v0.1.5.tar.gz
Platform: UNKNOWN
Requires-Dist: jupyter
